LICENSE
MANIFEST.in
README.rst
setup.cfg
setup.py
pytest_vyper/__init__.py
pytest_vyper/grammar.py
pytest_vyper/plugin.py
pytest_vyper/vyper.lark
pytest_vyper.egg-info/PKG-INFO
pytest_vyper.egg-info/SOURCES.txt
pytest_vyper.egg-info/dependency_links.txt
pytest_vyper.egg-info/entry_points.txt
pytest_vyper.egg-info/requires.txt
pytest_vyper.egg-info/top_level.txt