Metadata-Version: 2.1
Name: pytest-vyper
Version: 0.1.0
Summary: Plugin for the vyper smart contract language.
Home-page: https://github.com/sbellem/pytest-vyper
Author: Syvain Bellemare
Author-email: sbellem@gmail.com
Maintainer: Syvain Bellemare
Maintainer-email: sbellem@gmail.com
License: Apache Software License 2.0
Platform: UNKNOWN
Classifier: Development Status :: 2 - Pre-Alpha
Classifier: Framework :: Pytest
Classifier: Intended Audience :: Developers
Classifier: Topic :: Software Development :: Testing
Classifier: Programming Language :: Python
Classifier: Programming Language :: Python :: 3
Classifier: Programming Language :: Python :: 3.6
Classifier: Programming Language :: Python :: 3.7
Classifier: Programming Language :: Python :: 3.8
Classifier: Programming Language :: Python :: Implementation :: CPython
Classifier: Operating System :: OS Independent
Classifier: License :: OSI Approved :: Apache Software License
Requires-Python: >=3.6
Provides-Extra: dev
Provides-Extra: docs
Provides-Extra: tests
